authentik_diag_mcp/__init__.py
authentik_diag_mcp/server.py
authentik_diag_mcp-0.1.2.dist-info/METADATA
authentik_diag_mcp-0.1.2.dist-info/WHEEL
authentik_diag_mcp-0.1.2.dist-info/entry_points.txt
authentik_diag_mcp-0.1.2.dist-info/RECORD
