Metadata-Version: 2.4
Name: authentik-diag-mcp
Version: 0.1.2
Summary: MCP server for Authentik API with diagnostic and read-only capabilities
Project-URL: Homepage, https://github.com/goauthentik/authentik-diag-mcp
Project-URL: Repository, https://github.com/goauthentik/authentik-diag-mcp
Project-URL: Documentation, https://docs.goauthentik.io/
Author-email: Authentik MCP <hello@goauthentik.io>
Classifier: Development Status :: 4 - Beta
Classifier: Intended Audience :: Developers
Classifier: License :: OSI Approved :: MIT License
Classifier: Programming Language :: Python :: 3
Classifier: Programming Language :: Python :: 3.10
Classifier: Programming Language :: Python :: 3.11
Classifier: Programming Language :: Python :: 3.12
Requires-Python: >=3.10
Requires-Dist: httpx>=0.24.0
Requires-Dist: mcp>=1.0.0
Requires-Dist: pydantic>=2.0.0
Requires-Dist: typing-extensions>=4.0.0
Provides-Extra: dev
Requires-Dist: black>=23.0.0; extra == 'dev'
Requires-Dist: isort>=5.12.0; extra == 'dev'
Requires-Dist: mypy>=1.0.0; extra == 'dev'
Requires-Dist: pytest-asyncio>=0.21.0; extra == 'dev'
Requires-Dist: pytest>=7.0.0; extra == 'dev'
Requires-Dist: ruff>=0.1.2; extra == 'dev'
